MANIFEST.in
README.txt
setup.py
fastsst/__init__.py
fastsst/sst.py
fastsst.egg-info/PKG-INFO
fastsst.egg-info/SOURCES.txt
fastsst.egg-info/dependency_links.txt
fastsst.egg-info/not-zip-safe
fastsst.egg-info/requires.txt
fastsst.egg-info/top_level.txt
fastsst/util/__init__.py
fastsst/util/linear_algebra.py
tests/__init__.py
tests/test_linear_algebra.py
tests/test_sst.py
tests/test_data/__init__.py