Metadata-Version: 1.1
Name: fastsst
Version: 0.0.1
Summary: An implementation of change point detection algorithm.
Home-page: https://github.com/statefb/dtwalign
Author: Takehiro Suzuki
Author-email: UNKNOWN
License: MIT
Platform: UNKNOWN
Classifier: Programming Language :: Python :: 3.5
Classifier: Programming Language :: Python :: 3.6
Classifier: License :: OSI Approved :: GNU General Public License v2 (GPLv2)
Classifier: Topic :: Scientific/Engineering
